masa_ai/__init__.py
masa_ai/cli.py
masa_ai/configs/.secrets.yaml
masa_ai/configs/__init__.py
masa_ai/configs/config.py
masa_ai/configs/settings.yaml
masa_ai/connections/__init__.py
masa_ai/connections/api_connection.py
masa_ai/connections/xtwitter_connection.py
masa_ai/constants.py
masa_ai/docs/Makefile
masa_ai/docs/source/README.md
masa_ai/docs/source/_static
masa_ai/docs/source/conf.py
masa_ai/docs/source/index.rst
masa_ai/docs/source/modules/index.rst
masa_ai/docs/source/modules/masa_ai.cli.rst
masa_ai/docs/source/modules/masa_ai.configs.config.rst
masa_ai/docs/source/modules/masa_ai.configs.rst
masa_ai/docs/source/modules/masa_ai.connections.api_connection.rst
masa_ai/docs/source/modules/masa_ai.connections.rst
masa_ai/docs/source/modules/masa_ai.connections.xtwitter_connection.rst
masa_ai/docs/source/modules/masa_ai.constants.rst
masa_ai/docs/source/modules/masa_ai.masa.rst
masa_ai/docs/source/modules/masa_ai.orchestration.queue.rst
masa_ai/docs/source/modules/masa_ai.orchestration.request_manager.rst
masa_ai/docs/source/modules/masa_ai.orchestration.request_router.rst
masa_ai/docs/source/modules/masa_ai.orchestration.rst
masa_ai/docs/source/modules/masa_ai.orchestration.state_manager.rst
masa_ai/docs/source/modules/masa_ai.rst
masa_ai/docs/source/modules/masa_ai.tools.qc.error_handler.rst
masa_ai/docs/source/modules/masa_ai.tools.qc.exceptions.rst
masa_ai/docs/source/modules/masa_ai.tools.qc.logging_config.rst
masa_ai/docs/source/modules/masa_ai.tools.qc.qc_manager.rst
masa_ai/docs/source/modules/masa_ai.tools.qc.retry_manager.rst
masa_ai/docs/source/modules/masa_ai.tools.qc.rst
masa_ai/docs/source/modules/masa_ai.tools.rst
masa_ai/docs/source/modules/masa_ai.tools.scrape.rst
masa_ai/docs/source/modules/masa_ai.tools.scrape.scrape_xtwitter.rst
masa_ai/docs/source/modules/masa_ai.tools.utils.data_storage.rst
masa_ai/docs/source/modules/masa_ai.tools.utils.helper_functions.rst
masa_ai/docs/source/modules/masa_ai.tools.utils.paths.rst
masa_ai-0.2.7.dist-info/LICENSE
masa_ai-0.2.7.dist-info/METADATA
masa_ai-0.2.7.dist-info/WHEEL
masa_ai-0.2.7.dist-info/entry_points.txt
masa_ai-0.2.7.dist-info/RECORD
