Metadata-Version: 2.1
Name: masa-ai
Version: 0.2.7
Summary: MASA SDK - Masa's AI Software Architecture
Home-page: https://github.com/masa-finance/masa
License: MIT
Author: Masa AI
Author-email: engineering@masa.ai
Requires-Python: >=3.12,<4
Classifier: License :: OSI Approved :: MIT License
Classifier: Operating System :: OS Independent
Classifier: Programming Language :: Python :: 3
Classifier: Programming Language :: Python :: 3.12
Classifier: Programming Language :: Python :: 3.13
Requires-Dist: argparse (>=1.4.0,<2.0.0)
Requires-Dist: click (>=8.1.7,<9.0.0)
Requires-Dist: colorlog
Requires-Dist: dynaconf
Requires-Dist: feedparser
Requires-Dist: ipykernel
Requires-Dist: jupyter
Requires-Dist: loguru (>=0.7.2,<0.8.0)
Requires-Dist: myst-parser
Requires-Dist: notebook
Requires-Dist: numpy (>=2.0.1)
Requires-Dist: pandas
Requires-Dist: psycopg[binary]
Requires-Dist: python-dotenv
Requires-Dist: pyyaml (>=5.4)
Requires-Dist: recommonmark
Requires-Dist: requests
Requires-Dist: sphinx (<8.0.0)
Requires-Dist: sphinx_rtd_theme
Requires-Dist: tqdm
Requires-Dist: uuid (>=1.30,<2.0)
Project-URL: Repository, https://github.com/masa-finance/masa
